jsonabler/__init__.py
jsonabler/jsonable.py
jsonabler-0.2.2.dist-info/LICENSE
jsonabler-0.2.2.dist-info/METADATA
jsonabler-0.2.2.dist-info/WHEEL
jsonabler-0.2.2.dist-info/top_level.txt
jsonabler-0.2.2.dist-info/RECORD
