Metadata-Version: 2.1
Name: jsonabler
Version: 0.2.2
Summary: Python package for making your classes easy encodable to JSON string and vice-versa
Home-page: https://github.com/webfucktory/python-jsonabler
Author: webfucktory
Author-email: root@webfucktory.com
License: UNKNOWN
Platform: UNKNOWN
Classifier: Development Status :: 5 - Production/Stable
Classifier: Intended Audience :: Developers
Classifier: Natural Language :: English
Classifier: Operating System :: OS Independent
Classifier: Programming Language :: Python :: 3
Classifier: Programming Language :: Python :: 3 :: Only
Classifier: Programming Language :: Python :: 3.8
Classifier: Programming Language :: Python :: 3.9
Classifier: Programming Language :: Python :: 3.10
Requires-Python: >=3.8
License-File: LICENSE
